Metadata-Version: 2.1
Name: nazarov-da-lab2-task1-part1
Version: 0.1.1
Summary: Lagrange interpolation
Home-page: https://github.com/geranazavr555
Author: Georgiy Nazarov
Author-email: geranazavr555@yandex.ru
License: BSD 2-clause
Platform: UNKNOWN
Classifier: Development Status :: 1 - Planning
Classifier: Intended Audience :: Science/Research
Classifier: Programming Language :: Python :: 3.9
